<?xml version="1.0" encoding="ISO-8859-15"?>

<jonas-ejb-jar xmlns="http://www.objectweb.org/jonas/ns"
	           xmlns:xsi="http://www.w3.org/2001/XMLSchema-instance">

<!--
    xsi:schemaLocation="http://www.objectweb.org/jonas/ns
	http://www.objectweb.org/jonas/ns/jonas-ejb-jar_4_0.xsd" 
-->


  <jonas-session>
    <ejb-name>UsaMetalica1KEJB</ejb-name>
    <jndi-name>UsaMetalica1KHome</jndi-name>
    <session-timeout>28800</session-timeout>
    <jonas-ejb-ref>
      <ejb-ref-name>ejb/PreferencesEJB</ejb-ref-name>
      <jndi-name>PreferencesHome</jndi-name>
    </jonas-ejb-ref>
    <jonas-ejb-ref>
      <ejb-ref-name>ejb/SequenceHome</ejb-ref-name>
      <jndi-name>SequenceHome</jndi-name>
    </jonas-ejb-ref>
  </jonas-session>

  <jonas-session>
    <ejb-name>UsiMetalice1KEJB</ejb-name>
    <jndi-name>UsiMetalice1KHome</jndi-name>
  </jonas-session>

  <jonas-session>
    <ejb-name>UsaMetalica2KEJB</ejb-name>
    <jndi-name>UsaMetalica2KHome</jndi-name>
    <session-timeout>28800</session-timeout>
    <jonas-ejb-ref>
      <ejb-ref-name>ejb/PreferencesEJB</ejb-ref-name>
      <jndi-name>PreferencesHome</jndi-name>
    </jonas-ejb-ref>
    <jonas-ejb-ref>
      <ejb-ref-name>ejb/SequenceHome</ejb-ref-name>
      <jndi-name>SequenceHome</jndi-name>
    </jonas-ejb-ref>
  </jonas-session>

  <jonas-session>
    <ejb-name>UsiMetalice2KEJB</ejb-name>
    <jndi-name>UsiMetalice2KHome</jndi-name>
  </jonas-session>

  <jonas-session>
    <ejb-name>StandardOfferEJB</ejb-name>
    <jndi-name>StandardOfferHome</jndi-name>
    <session-timeout>28800</session-timeout>
    <jonas-ejb-ref>
      <ejb-ref-name>ejb/PreferencesEJB</ejb-ref-name>
      <jndi-name>PreferencesHome</jndi-name>
    </jonas-ejb-ref>
    <jonas-ejb-ref>
      <ejb-ref-name>ejb/SequenceHome</ejb-ref-name>
      <jndi-name>SequenceHome</jndi-name>
    </jonas-ejb-ref>
    <jonas-resource>
      <res-ref-name>jms/CF</res-ref-name>
      <jndi-name>CF</jndi-name>
    </jonas-resource>
    <jonas-message-destination-ref>
      <message-destination-ref-name>jms/priceUpdate</message-destination-ref-name>
      <jndi-name>Setum.UpdatePricesTopic</jndi-name>
    </jonas-message-destination-ref>
  </jonas-session>

  <jonas-session>
    <ejb-name>SistemEJB</ejb-name>
    <jndi-name>SistemHome</jndi-name>
    <session-timeout>28800</session-timeout>
    <jonas-ejb-ref>
      <ejb-ref-name>ejb/PreferencesEJB</ejb-ref-name>
      <jndi-name>PreferencesHome</jndi-name>
    </jonas-ejb-ref>
    <jonas-resource>
      <res-ref-name>jms/CF</res-ref-name>
      <jndi-name>CF</jndi-name>
    </jonas-resource>
    <jonas-message-destination-ref>
      <message-destination-ref-name>jms/priceUpdate</message-destination-ref-name>
      <jndi-name>Setum.UpdatePricesTopic</jndi-name>
    </jonas-message-destination-ref>
  </jonas-session>


  <jonas-session>
    <ejb-name>OtherProductsEJB</ejb-name>
    <jndi-name>OtherProductsHome</jndi-name>
    <session-timeout>28800</session-timeout>
    <jonas-ejb-ref>
      <ejb-ref-name>ejb/PreferencesEJB</ejb-ref-name>
      <jndi-name>PreferencesHome</jndi-name>
    </jonas-ejb-ref>
    <jonas-resource>
      <res-ref-name>jms/CF</res-ref-name>
      <jndi-name>CF</jndi-name>
    </jonas-resource>
    <jonas-message-destination-ref>
      <message-destination-ref-name>jms/priceUpdate</message-destination-ref-name>
      <jndi-name>Setum.UpdatePricesTopic</jndi-name>
    </jonas-message-destination-ref>
  </jonas-session>


  <jonas-session>
    <ejb-name>UsaStdNeechipataEJB</ejb-name>
    <jndi-name>UsaStdNeechipataHome</jndi-name>
    <session-timeout>28800</session-timeout>
    <jonas-ejb-ref>
      <ejb-ref-name>ejb/PreferencesEJB</ejb-ref-name>
      <jndi-name>PreferencesHome</jndi-name>
    </jonas-ejb-ref>
    <jonas-resource>
      <res-ref-name>jms/CF</res-ref-name>
      <jndi-name>CF</jndi-name>
    </jonas-resource>
    <jonas-message-destination-ref>
      <message-destination-ref-name>jms/priceUpdate</message-destination-ref-name>
      <jndi-name>Setum.UpdatePricesTopic</jndi-name>
    </jonas-message-destination-ref>
  </jonas-session>

  <jonas-session>
    <ejb-name>UsaStandardEJB</ejb-name>
    <jndi-name>UsaStandardHome</jndi-name>
    <session-timeout>28800</session-timeout>
    <jonas-ejb-ref>
      <ejb-ref-name>ejb/PreferencesEJB</ejb-ref-name>
      <jndi-name>PreferencesHome</jndi-name>
    </jonas-ejb-ref>
  </jonas-session>


  <jonas-session>
    <ejb-name>OfertaUsiStandardEJB</ejb-name>
    <jndi-name>OfertaUsiStandardHome</jndi-name>
    <session-timeout>28800</session-timeout>
    <jonas-ejb-ref>
      <ejb-ref-name>ejb/PreferencesEJB</ejb-ref-name>
      <jndi-name>PreferencesHome</jndi-name>
    </jonas-ejb-ref>
    <jonas-ejb-ref>
      <ejb-ref-name>ejb/SequenceHome</ejb-ref-name>
      <jndi-name>SequenceHome</jndi-name>
    </jonas-ejb-ref>
  </jonas-session>

  <jonas-session>
    <ejb-name>ArbitraryOfferEJB</ejb-name>
    <jndi-name>ArbitraryOfferHome</jndi-name>
    <session-timeout>28800</session-timeout>
    <jonas-ejb-ref>
      <ejb-ref-name>ejb/PreferencesEJB</ejb-ref-name>
      <jndi-name>PreferencesHome</jndi-name>
    </jonas-ejb-ref>
    <jonas-ejb-ref>
      <ejb-ref-name>ejb/SequenceHome</ejb-ref-name>
      <jndi-name>SequenceHome</jndi-name>
    </jonas-ejb-ref>
  </jonas-session>

  <jonas-session>
    <ejb-name>FereastraEJB</ejb-name>
    <jndi-name>FereastraHome</jndi-name>
    <session-timeout>28800</session-timeout>
    <jonas-ejb-ref>
      <ejb-ref-name>ejb/PreferencesEJB</ejb-ref-name>
      <jndi-name>PreferencesHome</jndi-name>
    </jonas-ejb-ref>
  </jonas-session>

  <jonas-session>
    <ejb-name>FereastraCategoryManagerEJB</ejb-name>
    <jndi-name>FereastraCategoryHome</jndi-name>
    <session-timeout>28800</session-timeout>
    <jonas-ejb-ref>
      <ejb-ref-name>ejb/PreferencesEJB</ejb-ref-name>
      <jndi-name>PreferencesHome</jndi-name>
    </jonas-ejb-ref>
  </jonas-session>

  <jonas-session>
    <ejb-name>GrilaVentilatieEJB</ejb-name>
    <jndi-name>GrilaVentilatieHome</jndi-name>
    <session-timeout>28800</session-timeout>
    <jonas-ejb-ref>
      <ejb-ref-name>ejb/PreferencesEJB</ejb-ref-name>
      <jndi-name>PreferencesHome</jndi-name>
    </jonas-ejb-ref>
  </jonas-session>

  <jonas-session>
    <ejb-name>GauriAerisireEJB</ejb-name>
    <jndi-name>GauriAerisireHome</jndi-name>
    <session-timeout>28800</session-timeout>
    <jonas-ejb-ref>
      <ejb-ref-name>ejb/PreferencesEJB</ejb-ref-name>
      <jndi-name>PreferencesHome</jndi-name>
    </jonas-ejb-ref>
  </jonas-session>

  <jonas-session>
    <ejb-name>SupraluminaEJB</ejb-name>
    <jndi-name>SupraluminaHome</jndi-name>
    <session-timeout>28800</session-timeout>
    <jonas-ejb-ref>
      <ejb-ref-name>ejb/PreferencesEJB</ejb-ref-name>
      <jndi-name>PreferencesHome</jndi-name>
    </jonas-ejb-ref>
  </jonas-session>

  <jonas-session>
    <ejb-name>SupraluminaCategoryManagerEJB</ejb-name>
    <jndi-name>SupraluminaCategoryHome</jndi-name>
    <session-timeout>28800</session-timeout>
    <jonas-ejb-ref>
      <ejb-ref-name>ejb/PreferencesEJB</ejb-ref-name>
      <jndi-name>PreferencesHome</jndi-name>
    </jonas-ejb-ref>
  </jonas-session>

  <jonas-session>
    <ejb-name>PanouLateralEJB</ejb-name>
    <jndi-name>PanouLateralHome</jndi-name>
    <session-timeout>28800</session-timeout>
    <jonas-ejb-ref>
      <ejb-ref-name>ejb/PreferencesEJB</ejb-ref-name>
      <jndi-name>PreferencesHome</jndi-name>
    </jonas-ejb-ref>
  </jonas-session>

  <jonas-session>
    <ejb-name>PanouLateralCategoryManagerEJB</ejb-name>
    <jndi-name>PanouLateralCategoryHome</jndi-name>
    <session-timeout>28800</session-timeout>
    <jonas-ejb-ref>
      <ejb-ref-name>ejb/PreferencesEJB</ejb-ref-name>
      <jndi-name>PreferencesHome</jndi-name>
    </jonas-ejb-ref>
  </jonas-session>


  <jonas-session>
    <ejb-name>FinisajeEJB</ejb-name>
    <jndi-name>FinisajeHome</jndi-name>
    <session-timeout>28800</session-timeout>
    <jonas-ejb-ref>
      <ejb-ref-name>ejb/PreferencesEJB</ejb-ref-name>
      <jndi-name>PreferencesHome</jndi-name>
    </jonas-ejb-ref>
  </jonas-session>


  <jonas-session>
    <ejb-name>ClientsEJB</ejb-name>
    <jndi-name>ClientsHome</jndi-name>
    <session-timeout>28800</session-timeout>
    <jonas-ejb-ref>
      <ejb-ref-name>ejb/PreferencesEJB</ejb-ref-name>
      <jndi-name>PreferencesHome</jndi-name>
    </jonas-ejb-ref>
  </jonas-session>

  <jonas-session>
    <ejb-name>GenericProductsEJB</ejb-name>
    <jndi-name>GenericProductsHome</jndi-name>
    <session-timeout>28800</session-timeout>
    <jonas-ejb-ref>
      <ejb-ref-name>ejb/PreferencesEJB</ejb-ref-name>
      <jndi-name>PreferencesHome</jndi-name>
    </jonas-ejb-ref>
    <jonas-ejb-ref>
      <ejb-ref-name>ejb/SequenceHome</ejb-ref-name>
      <jndi-name>SequenceHome</jndi-name>
    </jonas-ejb-ref>
  </jonas-session>

  <jonas-session>
    <ejb-name>UsiStdSelectionsEJB</ejb-name>
    <jndi-name>UsiStdSelectionsHome</jndi-name>
    <session-timeout>28800</session-timeout>
    <jonas-ejb-ref>
      <ejb-ref-name>ejb/PreferencesEJB</ejb-ref-name>
      <jndi-name>PreferencesHome</jndi-name>
    </jonas-ejb-ref>
    <jonas-ejb-ref>
      <ejb-ref-name>ejb/SequenceHome</ejb-ref-name>
      <jndi-name>SequenceHome</jndi-name>
    </jonas-ejb-ref>
  </jonas-session>

  <jonas-session>
    <ejb-name>OrdersEJB</ejb-name>
    <jndi-name>OrdersHome</jndi-name>
    <session-timeout>28800</session-timeout>
    <jonas-ejb-ref>
      <ejb-ref-name>ejb/PreferencesEJB</ejb-ref-name>
      <jndi-name>PreferencesHome</jndi-name>
    </jonas-ejb-ref>
    <jonas-ejb-ref>
      <ejb-ref-name>ejb/SequenceHome</ejb-ref-name>
      <jndi-name>SequenceHome</jndi-name>
    </jonas-ejb-ref>
  </jonas-session>



  <jonas-session>
    <ejb-name>RulesServerEJB</ejb-name>
    <jndi-name>RulesServerHome</jndi-name>
    <session-timeout>28800</session-timeout>
    <jonas-ejb-ref>
      <ejb-ref-name>ejb/PreferencesEJB</ejb-ref-name>
      <jndi-name>PreferencesHome</jndi-name>
    </jonas-ejb-ref>
  </jonas-session>

</jonas-ejb-jar>
